MANIFEST.in
README.md
setup.cfg
setup.py
micros_finder/__init__.py
micros_finder/cli.py
micros_finder/find_microsatellites.py
micros_finder/utils.py
microsatellites_finder.egg-info/PKG-INFO
microsatellites_finder.egg-info/SOURCES.txt
microsatellites_finder.egg-info/dependency_links.txt
microsatellites_finder.egg-info/entry_points.txt
microsatellites_finder.egg-info/pbr.json
microsatellites_finder.egg-info/top_level.txt