Metadata-Version: 1.1
Name: microsatellites-finder
Version: 1.1.0
Summary: Python package that searches for microsatellites in fasta sequences
Home-page: https://bitbucket.org/batterio/microsatellites_finder/
Author: Loris Mularoni
Author-email: loris.mularoni@gmail.com
License: The MIT License (MIT)
Download-URL: https://bitbucket.org/batterio/microsatellites_finder/get/1.1.0.tar.gz
Keywords: repeats,microsatellites
Platform: UNKNOWN
Classifier: Programming Language :: Python :: 3.4
